enular/__init__.py
enular/_analyzers.py
enular/analyzers.py
enular/base.py
enular/enular_analyzers.py
enular/enular_base.py
enular/enular_indicators.py
enular/enular_main.py
enular/enular_strategies.py
enular/enular_train.py
enular/fixes.py
enular/import_test.py
enular-0.2.3.dist-info/LICENSE
enular-0.2.3.dist-info/METADATA
enular-0.2.3.dist-info/WHEEL
enular-0.2.3.dist-info/top_level.txt
enular-0.2.3.dist-info/RECORD
