Metadata-Version: 2.1
Name: enular
Version: 0.2.3
Summary: Enular Library
Home-page: https://enular.com
Author: Adrian Chun Pang Wong, Dylan Fitzsimmons, Enular Limited
Author-email: adrian@enular.com
License: MIT
Platform: UNKNOWN
Classifier: Intended Audience :: Developers
Classifier: License :: OSI Approved :: MIT License
Classifier: Programming Language :: Python
Classifier: Programming Language :: Python :: 3
Classifier: Programming Language :: Python :: 3.6
Classifier: Programming Language :: Python :: 3.7
Classifier: Programming Language :: Python :: 3.8
Classifier: Programming Language :: Python :: 3.9
Classifier: Operating System :: OS Independent
Requires-Dist: backtrader
